{
  "_class": "group",
  "do_objectID": "74E82EB9-8F7B-4E55-A886-D6BE8895ACBD",
  "exportOptions": {
    "_class": "exportOptions",
    "exportFormats": [
    ],
    "includedLayerIds": [
    ],
    "layerOptions": 0,
    "shouldTrim": false
  },
  "frame": {
    "_class": "rect",
    "constrainProportions": false,
    "height": 16,
    "width": 81,
    "x": 0,
    "y": 0
  },
  "hasClickThrough": false,
  "isFlippedHorizontal": false,
  "isFlippedVertical": false,
  "isLocked": false,
  "isVisible": true,
  "layerListExpandedType": 0,
  "layers": [
    {
      "class": "text",
      "id": "A5C8A687-062C-48E7-947B-916E4C8FFAE5"
    },
    {
      "class": "text",
      "id": "7910A606-5EE6-442C-9705-3E5B6B28A4A5"
    }
  ],
  "name": "Group 5",
  "nameIsFixed": false,
  "originalObjectID": "4D43B310-0EE9-4740-BD34-E0E454179DC1",
  "resizingConstraint": 63,
  "resizingType": 0,
  "rotation": 0,
  "shouldBreakMaskChain": false,
  "style": {
    "_class": "style",
    "endDecorationType": 0,
    "miterLimit": 10,
    "startDecorationType": 0
  },
  "userInfo": {
    "com.animaapp.stc-sketch-plugin": {
      "kModelPropertiesKey": {
      }
    }
  }
}