{
  "_class": "group",
  "do_objectID": "2411696C-EBF8-414A-8C37-767F3292037B",
  "exportOptions": {
    "_class": "exportOptions",
    "exportFormats": [
    ],
    "includedLayerIds": [
    ],
    "layerOptions": 0,
    "shouldTrim": false
  },
  "frame": {
    "_class": "rect",
    "constrainProportions": false,
    "height": 41,
    "width": 366,
    "x": 11,
    "y": 9
  },
  "hasClickThrough": false,
  "isFlippedHorizontal": false,
  "isFlippedVertical": false,
  "isLocked": false,
  "isVisible": true,
  "layerListExpandedType": 0,
  "layers": [
    {
      "class": "group",
      "id": "AA8544E4-71AF-415C-B262-F11C2EBCE1FC"
    },
    {
      "class": "group",
      "id": "22F84F8C-5C51-43D3-90E4-17EC52EA1ACE"
    },
    {
      "class": "group",
      "id": "131EE9AA-41D1-407A-B49C-D7D67EF92867"
    },
    {
      "class": "group",
      "id": "480F6BC1-B370-447D-933B-F1A286492095"
    },
    {
      "class": "group",
      "id": "D8E018EA-CD0E-492A-AFFA-DEBAE4B9DD8E"
    },
    {
      "class": "group",
      "id": "BFEC88EC-0307-4908-AB2F-DAC1D405F070"
    },
    {
      "class": "shapeGroup",
      "id": "98BD8F91-3DE8-4EEA-A4A7-2409B8FE813B"
    },
    {
      "class": "shapeGroup",
      "id": "88356366-30F5-4666-B782-DB4F307C4C17"
    },
    {
      "class": "shapeGroup",
      "id": "F4607ABE-CB51-40D1-A61E-FB5BDC5BA688"
    }
  ],
  "name": "Label",
  "nameIsFixed": false,
  "originalObjectID": "D1E3EE68-131B-4369-A851-6B33A68152F9",
  "resizingConstraint": 63,
  "resizingType": 0,
  "rotation": 0,
  "shouldBreakMaskChain": false,
  "style": {
    "_class": "style",
    "endDecorationType": 0,
    "miterLimit": 10,
    "startDecorationType": 0
  },
  "userInfo": {
    "com.animaapp.stc-sketch-plugin": {
      "kModelPropertiesKey": {
      }
    }
  }
}