{
  "_class": "rectangle",
  "booleanOperation": -1,
  "do_objectID": "EE2ABC56-AA89-48F8-A7B3-5EC623C8B360",
  "edited": true,
  "exportOptions": {
    "_class": "exportOptions",
    "exportFormats": [
    ],
    "includedLayerIds": [
    ],
    "layerOptions": 0,
    "shouldTrim": false
  },
  "fixedRadius": 0,
  "frame": {
    "_class": "rect",
    "constrainProportions": false,
    "height": 7,
    "width": 11,
    "x": 1,
    "y": 3
  },
  "hasConvertedToNewRoundCorners": true,
  "isFlippedHorizontal": false,
  "isFlippedVertical": false,
  "isLocked": false,
  "isVisible": true,
  "layerListExpandedType": 0,
  "name": "Rectangle 7",
  "nameIsFixed": false,
  "path": {
    "_class": "path",
    "isClosed": true,
    "pointRadiusBehaviour": 0,
    "points": [
      {
        "_class": "curvePoint",
        "cornerRadius": 0,
        "curveFrom": "{0, 0}",
        "curveMode": 1,
        "curveTo": "{0, 0}",
        "hasCurveFrom": false,
        "hasCurveTo": false,
        "point": "{0, 0}"
      },
      {
        "_class": "curvePoint",
        "cornerRadius": 0,
        "curveFrom": "{1, 0.8571428571428571}",
        "curveMode": 1,
        "curveTo": "{1, 0.8571428571428571}",
        "hasCurveFrom": false,
        "hasCurveTo": false,
        "point": "{1, 0.8571428571428571}"
      },
      {
        "_class": "curvePoint",
        "cornerRadius": 0,
        "curveFrom": "{1, 1}",
        "curveMode": 1,
        "curveTo": "{1, 1}",
        "hasCurveFrom": false,
        "hasCurveTo": false,
        "point": "{1, 1}"
      },
      {
        "_class": "curvePoint",
        "cornerRadius": 0,
        "curveFrom": "{0, 0.14285714285714285}",
        "curveMode": 1,
        "curveTo": "{0, 0.14285714285714285}",
        "hasCurveFrom": false,
        "hasCurveTo": false,
        "point": "{0, 0.14285714285714285}"
      }
    ]
  },
  "resizingConstraint": 63,
  "resizingType": 0,
  "rotation": 0,
  "shouldBreakMaskChain": false,
  "userInfo": {
    "com.animaapp.stc-sketch-plugin": {
      "kModelPropertiesKey": {
      }
    }
  }
}