{
  "_class": "shapeGroup",
  "clippingMaskMode": 0,
  "do_objectID": "D426449B-D84F-46FB-9563-235579AA3A75",
  "exportOptions": {
    "_class": "exportOptions",
    "exportFormats": [
    ],
    "includedLayerIds": [
    ],
    "layerOptions": 0,
    "shouldTrim": false
  },
  "frame": {
    "_class": "rect",
    "constrainProportions": false,
    "height": 9.5,
    "width": 24.5,
    "x": 330,
    "y": 5.5
  },
  "hasClickThrough": false,
  "hasClippingMask": false,
  "isFlippedHorizontal": false,
  "isFlippedVertical": false,
  "isLocked": false,
  "isVisible": true,
  "layerListExpandedType": 0,
  "layers": [
    {
      "class": "shapePath",
      "id": "9D0D2D1E-D562-4FEC-9FF5-EB6C19E8F90B"
    },
    {
      "class": "shapePath",
      "id": "D0D732B8-25D5-4E75-ADFC-3E2C0B8B7D3A"
    },
    {
      "class": "rectangle",
      "id": "FA612E04-801E-4B07-A170-98A21570DF2E"
    },
    {
      "class": "rectangle",
      "id": "121C9C2B-9F85-4F92-B13A-7CBA210F6F50"
    }
  ],
  "name": "Battery",
  "nameIsFixed": true,
  "resizingConstraint": 44,
  "resizingType": 1,
  "rotation": 0,
  "shouldBreakMaskChain": false,
  "style": {
    "_class": "style",
    "endDecorationType": 0,
    "fills": [
      {
        "_class": "fill",
        "color": {
          "_class": "color",
          "alpha": 1,
          "blue": 0.6784313725490196,
          "green": 0.6784313725490196,
          "red": 0.6784313725490196
        },
        "fillType": 0,
        "isEnabled": true,
        "noiseIndex": 0,
        "noiseIntensity": 0,
        "patternFillType": 1,
        "patternTileScale": 1
      }
    ],
    "miterLimit": 10,
    "startDecorationType": 0
  },
  "userInfo": {
    "com.animaapp.stc-sketch-plugin": {
      "kModelPropertiesKey": {
      }
    }
  },
  "windingRule": 0
}