{
  "_class": "group",
  "do_objectID": "A140C479-9B5D-47B7-8FFA-1E67410ABB45",
  "exportOptions": {
    "_class": "exportOptions",
    "exportFormats": [
    ],
    "includedLayerIds": [
    ],
    "layerOptions": 0,
    "shouldTrim": false
  },
  "frame": {
    "_class": "rect",
    "constrainProportions": false,
    "height": 15,
    "width": 4,
    "x": 1013.33333333333,
    "y": 7.75
  },
  "hasClickThrough": false,
  "isFlippedHorizontal": false,
  "isFlippedVertical": false,
  "isLocked": false,
  "isVisible": true,
  "layerListExpandedType": 0,
  "layers": [
    {
      "class": "shapeGroup",
      "id": "C7A7F9EF-EBEF-443A-8D0D-7579F6CF318F"
    },
    {
      "class": "shapeGroup",
      "id": "D105F2E7-7053-4E76-8F8D-5A563AA0D0B2"
    },
    {
      "class": "shapeGroup",
      "id": "C5762C6F-B0B5-4809-9827-472C3F923FEE"
    }
  ],
  "name": "Chrome more menu",
  "nameIsFixed": true,
  "resizingConstraint": 63,
  "resizingType": 0,
  "rotation": 0,
  "shouldBreakMaskChain": false,
  "style": {
    "_class": "style",
    "endDecorationType": 0,
    "miterLimit": 10,
    "startDecorationType": 0
  },
  "userInfo": {
    "com.animaapp.stc-sketch-plugin": {
      "kModelPropertiesKey": {
      }
    }
  }
}